examples/__init__.py
synthesis/__init__.py
synthesis/evaluation/__init__.py
synthesis/evaluation/_base.py
synthesis/evaluation/efficacy.py
synthesis/evaluation/evaluator.py
synthesis/evaluation/experiment.py
synthesis/evaluation/metrics.py
synthesis/evaluation/visual.py
synthesis/synthesizers/__init__.py
synthesis/synthesizers/_base.py
synthesis/synthesizers/contingency.py
synthesis/synthesizers/marginal.py
synthesis/synthesizers/privbayes.py
synthesis/synthesizers/utils.py
synthesis/transformers/__init__.py
synthesis/transformers/_base.py
synthesis/transformers/deidentification.py
synthesis/transformers/generalization.py
synthesis/transformers/sequence.py
tests/__init__.py
tests/transformers/__init__.py
tests/transformers/test_generalization.py
synthetic_data_generation-0.1.14.dist-info/LICENSE
synthetic_data_generation-0.1.14.dist-info/METADATA
synthetic_data_generation-0.1.14.dist-info/WHEEL
synthetic_data_generation-0.1.14.dist-info/top_level.txt
synthetic_data_generation-0.1.14.dist-info/RECORD
