Metadata-Version: 2.1
Name: synthetic-data-generation
Version: 0.1.14
Summary: Algorithms for generating synthetic data
Author: Daan Knoors
Author-email: d.knoors@gmail.com
License-File: LICENSE
Requires-Dist: diffprivlib (>=0.6.3)
Requires-Dist: dill (>=0.3.4)
Requires-Dist: dython (==0.6.8)
Requires-Dist: joblib (>=1.0.1)
Requires-Dist: lifelines (>=0.26.0)
Requires-Dist: matplotlib (>=3.4.3)
Requires-Dist: numpy (>=1.21.2)
Requires-Dist: pandas (>=1.3.2)
Requires-Dist: pyjanitor (>=0.21.2)
Requires-Dist: pandas-flavor (==0.6.0)
Requires-Dist: scikit-learn (>=1.0.2)
Requires-Dist: scipy (>=1.7.1)
Requires-Dist: seaborn (>=0.12.0)
Requires-Dist: thomas-core (==0.1.3)
Provides-Extra: interactive
Requires-Dist: jupyter ; extra == 'interactive'
